setup.py
dsnd_probability_distributions/Binomialdistribution.py
dsnd_probability_distributions/Gaussiandistribution.py
dsnd_probability_distributions/Generaldistribution.py
dsnd_probability_distributions/__init__.py
dsnd_probability_distributions.egg-info/PKG-INFO
dsnd_probability_distributions.egg-info/SOURCES.txt
dsnd_probability_distributions.egg-info/dependency_links.txt
dsnd_probability_distributions.egg-info/not-zip-safe
dsnd_probability_distributions.egg-info/top_level.txt