Metadata-Version: 1.0
Name: dsnd-probability-distributions
Version: 0.1
Summary: Gaussian and Binomial distributions
Home-page: UNKNOWN
Author: Lindsey Jackson
Author-email: lmjacks7@gmail.com
License: UNKNOWN
Platform: UNKNOWN
